[
    {
        "EventId": 223, 
        "Transform": 5, 
        "TimeCreated": "2018-02-19T17:43:13.685+00:00", 
        "Accelerometer": {
            "TriggerCount": 0, 
            "SampleRateHz": 1000, 
            "Offsets": {
                "Y": 0, 
                "X": 0, 
                "Z": 0
            }
        }, 
        "HardwareId": 210648, 
        "Gyro": {
            "TriggerCount": 0, 
            "SampleRateHz": 765, 
            "Offsets": {
                "Y": 0, 
                "X": 0, 
                "Z": 0
            }
        }, 
        "SerialNumber": "6EQS", 
        "AccelerometerSamples": {
            "Y": [
                -1, 
                0, 
                0, 
                -1, 
                -1, 
                -1, 
                -1, 
                0, 
                0, 
                -1, 
                0, 
                0, 
                -1, 
                0, 
                -1, 
                0, 
                -8, 
                -15, 
                -19, 
                -5, 
                6, 
                -12, 
                -2, 
                22, 
                11, 
                -2, 
                -2, 
                2, 
                3, 
                -2, 
                -5, 
                3, 
                1, 
                -2, 
                -3, 
                -4, 
                -1, 
                1, 
                2, 
                1, 
                0, 
                -1, 
                -3, 
                -2, 
                -4, 
                -4, 
                -3, 
                -1, 
                -2, 
                -3, 
                -1, 
                0, 
                -1, 
                -1, 
                -1, 
                0, 
                1, 
                0, 
                0, 
                1, 
                1, 
                0, 
                1, 
                1, 
                2, 
                2, 
                2, 
                2, 
                2, 
                1, 
                1, 
                1, 
                1, 
                1, 
                2, 
                1, 
                1, 
                2, 
                2, 
                1, 
                1, 
                1, 
                1, 
                0, 
                1, 
                1, 
                1, 
                0, 
                0, 
                0, 
                0, 
                0, 
                0, 
                0, 
                1, 
                1
            ], 
            "X": [
                0, 
                -1, 
                0, 
                0, 
                0, 
                0, 
                0, 
                0, 
                0, 
                0, 
                0, 
                0, 
                0, 
                0, 
                0, 
                1, 
                -6, 
                -49, 
                -97, 
                -36, 
                4, 
                -32, 
                -22, 
                1, 
                27, 
                17, 
                -6, 
                -10, 
                1, 
                10, 
                8, 
                2, 
                3, 
                4, 
                7, 
                7, 
                7, 
                6, 
                5, 
                -1, 
                0, 
                0, 
                1, 
                5, 
                7, 
                5, 
                4, 
                6, 
                8, 
                9, 
                9, 
                7, 
                9, 
                11, 
                9, 
                9, 
                10, 
                11, 
                10, 
                9, 
                9, 
                8, 
                8, 
                7, 
                5, 
                6, 
                5, 
                5, 
                5, 
                5, 
                5, 
                5, 
                5, 
                4, 
                5, 
                4, 
                4, 
                4, 
                3, 
                4, 
                3, 
                2, 
                2, 
                2, 
                2, 
                1, 
                2, 
                2, 
                2, 
                1, 
                1, 
                1, 
                1, 
                1, 
                -3, 
                -9
            ], 
            "Length": 96, 
            "Z": [
                0, 
                -1, 
                -1, 
                -1, 
                -1, 
                -1, 
                0, 
                0, 
                0, 
                0, 
                -1, 
                0, 
                -1, 
                0, 
                -1, 
                0, 
                -2, 
                -29, 
                -23, 
                -6, 
                -12, 
                -3, 
                7, 
                31, 
                38, 
                -9, 
                -8, 
                -3, 
                -8, 
                -12, 
                -10, 
                -8, 
                -6, 
                2, 
                4, 
                1, 
                2, 
                15, 
                13, 
                10, 
                5, 
                0, 
                -4, 
                -2, 
                -1, 
                -3, 
                -2, 
                0, 
                1, 
                4, 
                5, 
                3, 
                6, 
                5, 
                6, 
                5, 
                3, 
                2, 
                2, 
                1, 
                1, 
                1, 
                1, 
                1, 
                1, 
                1, 
                1, 
                1, 
                1, 
                0, 
                1, 
                0, 
                0, 
                0, 
                0, 
                0, 
                0, 
                0, 
                0, 
                0, 
                0, 
                1, 
                0, 
                0, 
                -1, 
                0, 
                -1, 
                -1, 
                0, 
                0, 
                0, 
                0, 
                1, 
                0, 
                -2, 
                -4
            ]
        }, 
        "GyroSamples": {
            "Y": [
                1023, 
                511, 
                -1, 
                255, 
                511, 
                -6, 
                2047, 
                2047, 
                2303, 
                2047, 
                2047, 
                1279, 
                -7, 
                1023, 
                255, 
                -2048, 
                -2560, 
                -1792, 
                22528, 
                446, 
                -22782, 
                -17914, 
                21761, 
                -22030, 
                -10772, 
                16629, 
                -2578, 
                -31494, 
                -4351, 
                7440, 
                -6894, 
                -1519, 
                -15342, 
                7186, 
                23312, 
                1807, 
                7433, 
                7432, 
                6664, 
                9225, 
                1292, 
                -27379, 
                13325, 
                -29426, 
                18448, 
                18448, 
                -22256, 
                -19440, 
                -26609, 
                19214, 
                -32243, 
                781, 
                19468, 
                3083, 
                -10741, 
                3339, 
                3338, 
                2825, 
                5385, 
                -29688, 
                2014, 
                6407, 
                18182, 
                -13306, 
                28165, 
                12805, 
                -764, 
                1149, 
                21508, 
                9987, 
                20995, 
                -15102, 
                32258, 
                -26879, 
                323, 
                17920, 
                20224, 
                4096, 
                -20481, 
                10493
            ], 
            "X": [
                -1537, 
                -2305, 
                -1793, 
                -1025, 
                -1281, 
                2047, 
                -1281, 
                -1537, 
                -769, 
                -769, 
                -1281, 
                -1793, 
                2047, 
                -1025, 
                -1025, 
                2047, 
                3583, 
                4095, 
                5887, 
                2047, 
                -2305, 
                -20993, 
                -30209, 
                -18689, 
                -25089, 
                7679, 
                2047, 
                28927, 
                -11521, 
                -13825, 
                -12033, 
                -11777, 
                30975, 
                18687, 
                -26369, 
                15615, 
                -29697, 
                -769, 
                -9217, 
                -23809, 
                24575, 
                22015, 
                9983, 
                -28673, 
                18943, 
                3583, 
                17919, 
                7167, 
                14335, 
                31487, 
                -16385, 
                1023, 
                25855, 
                2047, 
                -17153, 
                24063, 
                -2305, 
                -5633, 
                7935, 
                25343, 
                2047, 
                22527, 
                -13569, 
                20479, 
                -28417, 
                13311, 
                -8961, 
                2047, 
                2303, 
                -24577, 
                10495, 
                27391, 
                5631, 
                -20993, 
                2047, 
                -8705, 
                31487, 
                6399, 
                18943, 
                -7169
            ], 
            "Length": 80, 
            "Z": [
                1792, 
                1792, 
                1023, 
                256, 
                768, 
                6, 
                768, 
                768, 
                1536, 
                1280, 
                768, 
                768, 
                3, 
                768, 
                1536, 
                1535, 
                2303, 
                1023, 
                768, 
                1622, 
                -32242, 
                -10244, 
                -24535, 
                13383, 
                -9656, 
                13085, 
                1648, 
                20220, 
                22513, 
                -22783, 
                21009, 
                14367, 
                25134, 
                -24006, 
                -21953, 
                -30910, 
                -21962, 
                -28886, 
                -2784, 
                26138, 
                -29928, 
                -25577, 
                14360, 
                -25319, 
                -7910, 
                -4583, 
                20501, 
                -29677, 
                30737, 
                -26098, 
                -3322, 
                -28668, 
                -9470, 
                178, 
                -1282, 
                253, 
                4859, 
                6903, 
                1013, 
                -3853, 
                -3516, 
                -9999, 
                -25104, 
                26351, 
                -8977, 
                -23569, 
                26094, 
                -4405, 
                -1554, 
                -9235, 
                -13077, 
                -27160, 
                30184, 
                17128, 
                -5897, 
                -10775, 
                -27671, 
                25065, 
                -10264, 
                -1814
            ]
        }, 
        "DeviceRevision": 0, 
        "TimeReceivedBySlc": "2018-02-19T17:43:29.848701+00:00", 
        "DeviceType": 0, 
        "Flags": 0, 
        "AccelerometerThreshold": 0, 
        "GyroThreshold": 0, 
        "FirmwareVersion": {
            "Major": 0, 
            "Build": 0, 
            "Minor": 0, 
            "IsModified": false
        }, 
        "TimeCreated_Uncorrected": null
    }, 
    {
        "EventId": 222, 
        "Transform": 5, 
        "TimeCreated": "2018-02-19T17:43:13.847+00:00", 
        "Accelerometer": {
            "TriggerCount": 0, 
            "SampleRateHz": 1000, 
            "Offsets": {
                "Y": 0, 
                "X": 0, 
                "Z": 0
            }
        }, 
        "HardwareId": 210620, 
        "Gyro": {
            "TriggerCount": 0, 
            "SampleRateHz": 765, 
            "Offsets": {
                "Y": 0, 
                "X": 0, 
                "Z": 0
            }
        }, 
        "SerialNumber": "6EPW", 
        "AccelerometerSamples": {
            "Y": [
                -1, 
                -1, 
                -1, 
                -1, 
                -1, 
                -1, 
                -1, 
                -1, 
                -1, 
                -1, 
                -1, 
                -1, 
                -1, 
                -1, 
                -1, 
                -2, 
                -6, 
                -7, 
                -12, 
                -3, 
                -1, 
                -2, 
                -3, 
                -4, 
                -4, 
                -4, 
                -7, 
                1, 
                4, 
                2, 
                1, 
                0, 
                -1, 
                -1, 
                -1, 
                0, 
                1, 
                1, 
                1, 
                -1, 
                -1, 
                -1, 
                -1, 
                0, 
                -1, 
                -1, 
                -1, 
                -1, 
                -1, 
                -2, 
                -3, 
                -2, 
                -1, 
                -1, 
                -1, 
                -1, 
                -1, 
                -1, 
                0, 
                0, 
                0, 
                1, 
                1, 
                2, 
                -6, 
                5, 
                3, 
                0, 
                1, 
                0, 
                1, 
                1, 
                0, 
                1, 
                1, 
                0, 
                0, 
                0, 
                0, 
                0, 
                0, 
                0, 
                0, 
                0, 
                0, 
                0, 
                0, 
                0, 
                1, 
                0, 
                0, 
                0, 
                -1, 
                -2, 
                -3, 
                -3
            ], 
            "X": [
                -1, 
                -2, 
                -2, 
                -2, 
                -1, 
                -1, 
                -2, 
                -1, 
                -1, 
                -1, 
                -2, 
                -1, 
                -2, 
                -2, 
                -1, 
                -1, 
                -10, 
                -36, 
                -55, 
                -28, 
                -18, 
                -27, 
                -25, 
                -16, 
                -20, 
                -10, 
                -5, 
                -1, 
                5, 
                10, 
                8, 
                8, 
                8, 
                3, 
                3, 
                5, 
                9, 
                12, 
                12, 
                11, 
                9, 
                8, 
                10, 
                10, 
                10, 
                9, 
                6, 
                4, 
                3, 
                4, 
                4, 
                4, 
                2, 
                2, 
                2, 
                2, 
                2, 
                3, 
                4, 
                4, 
                3, 
                3, 
                4, 
                4, 
                4, 
                3, 
                9, 
                3, 
                2, 
                2, 
                1, 
                2, 
                2, 
                1, 
                2, 
                1, 
                1, 
                0, 
                1, 
                0, 
                0, 
                0, 
                1, 
                0, 
                0, 
                0, 
                0, 
                -1, 
                0, 
                -1, 
                -1, 
                -1, 
                -2, 
                -3, 
                -6, 
                -8
            ], 
            "Length": 96, 
            "Z": [
                -1, 
                0, 
                -1, 
                0, 
                0, 
                -1, 
                0, 
                -1, 
                0, 
                0, 
                -1, 
                0, 
                0, 
                0, 
                0, 
                5, 
                -4, 
                -9, 
                -3, 
                0, 
                0, 
                7, 
                0, 
                3, 
                5, 
                5, 
                3, 
                1, 
                -1, 
                -3, 
                0, 
                -1, 
                -4, 
                -2, 
                -2, 
                -2, 
                -2, 
                -3, 
                -4, 
                -5, 
                -3, 
                -1, 
                -3, 
                -2, 
                -2, 
                -2, 
                0, 
                -1, 
                -1, 
                0, 
                -1, 
                0, 
                -1, 
                -1, 
                0, 
                -1, 
                0, 
                -1, 
                -1, 
                -1, 
                -1, 
                -1, 
                -1, 
                0, 
                -1, 
                2, 
                -3, 
                1, 
                0, 
                0, 
                1, 
                0, 
                0, 
                0, 
                0, 
                -1, 
                0, 
                0, 
                -1, 
                0, 
                -1, 
                -1, 
                -1, 
                -1, 
                -1, 
                -1, 
                -1, 
                -1, 
                -1, 
                -2, 
                -2, 
                -1, 
                -1, 
                -3, 
                -1, 
                -1
            ]
        }, 
        "GyroSamples": {
            "Y": [
                9215, 
                9727, 
                9471, 
                8959, 
                8959, 
                9727, 
                10239, 
                9983, 
                10239, 
                -8, 
                9471, 
                8959, 
                8191, 
                2815, 
                511, 
                2048, 
                14847, 
                -11264, 
                18433, 
                -3839, 
                8702, 
                -28420, 
                15865, 
                -6151, 
                -24325, 
                30204, 
                -14594, 
                5630, 
                -15876, 
                -3844, 
                -25860, 
                31997, 
                -29699, 
                5116, 
                -4355, 
                -27395, 
                21502, 
                29438, 
                16894, 
                -506, 
                13309, 
                2813, 
                5885, 
                -5635, 
                3580, 
                12796, 
                -1540, 
                15612, 
                -880, 
                14588, 
                509, 
                2045, 
                17405, 
                29181, 
                -13826, 
                -7681, 
                -32258, 
                -28673, 
                91, 
                -23552, 
                14848, 
                7424, 
                -23296, 
                16128, 
                -5632, 
                -28160, 
                2561, 
                25089, 
                29185, 
                15361, 
                3329, 
                3073, 
                8193, 
                19714, 
                26882, 
                28418, 
                24578, 
                767, 
                12291, 
                -5629
            ], 
            "X": [
                -2561, 
                -2561, 
                -2561, 
                -1793, 
                -2049, 
                -1537, 
                -769, 
                -513, 
                -1281, 
                2047, 
                -1281, 
                -1793, 
                -769, 
                -1537, 
                -257, 
                255, 
                -7937, 
                17407, 
                -2049, 
                8447, 
                9215, 
                4863, 
                -12033, 
                -5633, 
                31743, 
                -3329, 
                29183, 
                7167, 
                -6657, 
                24063, 
                -27905, 
                3071, 
                16383, 
                -21761, 
                25855, 
                -7425, 
                11775, 
                14847, 
                12031, 
                2047, 
                -9217, 
                -15361, 
                -29953, 
                23551, 
                -12033, 
                19967, 
                13823, 
                25599, 
                2047, 
                -13057, 
                3327, 
                15359, 
                20479, 
                30719, 
                -25345, 
                13823, 
                -28417, 
                25087, 
                2047, 
                -30721, 
                -23809, 
                -23297, 
                -13569, 
                -9729, 
                -4609, 
                -1537, 
                3071, 
                14335, 
                -22785, 
                -15617, 
                -11777, 
                -9985, 
                -5377, 
                9727, 
                20735, 
                -23809, 
                -7681, 
                2047, 
                2815, 
                1535
            ], 
            "Length": 80, 
            "Z": [
                13312, 
                12800, 
                12544, 
                12800, 
                13056, 
                13056, 
                12544, 
                12288, 
                12800, 
                38, 
                14592, 
                14336, 
                13056, 
                12544, 
                12800, 
                12032, 
                8959, 
                29951, 
                -29441, 
                -25616, 
                -5909, 
                3813, 
                13541, 
                -19997, 
                20447, 
                -16677, 
                16342, 
                -30760, 
                15577, 
                -21798, 
                2011, 
                14556, 
                30685, 
                29919, 
                27873, 
                -8987, 
                -1815, 
                -1300, 
                -1553, 
                -3569, 
                -28937, 
                -21511, 
                5626, 
                -25862, 
                4604, 
                -28675, 
                24317, 
                -15617, 
                -80, 
                -25600, 
                1, 
                4354, 
                -24573, 
                -15100, 
                19462, 
                -4857, 
                -3576, 
                -13047, 
                2907, 
                -2804, 
                -25843, 
                -1010, 
                -12530, 
                -23025, 
                30991, 
                27152, 
                -31471, 
                -13295, 
                -26863, 
                17, 
                26897, 
                -16879, 
                2321, 
                27665, 
                -4847, 
                17937, 
                2321, 
                4449, 
                32017, 
                23824
            ]
        }, 
        "DeviceRevision": 0, 
        "TimeReceivedBySlc": "2018-02-19T17:43:43.815845+00:00", 
        "DeviceType": 0, 
        "Flags": 0, 
        "AccelerometerThreshold": 0, 
        "GyroThreshold": 0, 
        "FirmwareVersion": {
            "Major": 0, 
            "Build": 0, 
            "Minor": 0, 
            "IsModified": false
        }, 
        "TimeCreated_Uncorrected": null
    }
]