[
    {
        "EventId": 65, 
        "Transform": 5, 
        "TimeCreated": "2018-01-29T21:06:10.695+00:00", 
        "Accelerometer": {
            "TriggerCount": 0, 
            "SampleRateHz": 1000, 
            "Offsets": {
                "Y": 0, 
                "X": 0, 
                "Z": 0
            }
        }, 
        "HardwareId": 210629, 
        "Gyro": {
            "TriggerCount": 0, 
            "SampleRateHz": 765, 
            "Offsets": {
                "Y": 0, 
                "X": 0, 
                "Z": 0
            }
        }, 
        "SerialNumber": "6EQ5", 
        "AccelerometerSamples": {
            "Y": [
                0, 
                0, 
                0, 
                0, 
                0, 
                0, 
                0, 
                0, 
                0, 
                -1, 
                0, 
                0, 
                0, 
                0, 
                0, 
                -4, 
                -40, 
                -55, 
                -22, 
                -6, 
                -1, 
                2, 
                17, 
                31, 
                25, 
                16, 
                0, 
                -7, 
                -6, 
                -3, 
                -1, 
                1, 
                1, 
                0, 
                2, 
                3, 
                5, 
                5, 
                4, 
                1, 
                1, 
                -1, 
                -2, 
                -4, 
                -5, 
                -4, 
                -2, 
                0, 
                2, 
                3, 
                4, 
                6, 
                7, 
                7, 
                4, 
                0, 
                0, 
                -1, 
                0, 
                -1, 
                -1, 
                -1, 
                0, 
                1, 
                2, 
                2, 
                3, 
                3, 
                3, 
                4, 
                2, 
                2, 
                2, 
                1, 
                1, 
                1, 
                1, 
                1, 
                1, 
                1, 
                2, 
                2, 
                2, 
                2, 
                1, 
                1, 
                1, 
                1, 
                0, 
                0, 
                0, 
                0, 
                0, 
                1, 
                1, 
                1
            ], 
            "X": [
                0, 
                0, 
                0, 
                -1, 
                -1, 
                0, 
                -1, 
                -1, 
                -1, 
                -1, 
                0, 
                -1, 
                0, 
                -1, 
                -1, 
                0, 
                12, 
                49, 
                45, 
                16, 
                1, 
                -3, 
                -16, 
                -24, 
                -29, 
                -30, 
                -29, 
                -19, 
                -12, 
                -6, 
                -3, 
                0, 
                5, 
                11, 
                16, 
                14, 
                11, 
                6, 
                3, 
                0, 
                -1, 
                -2, 
                -4, 
                -4, 
                -4, 
                -5, 
                -7, 
                -6, 
                -6, 
                -6, 
                -8, 
                -8, 
                -8, 
                -8, 
                -4, 
                -3, 
                -1, 
                -1, 
                0, 
                1, 
                3, 
                4, 
                4, 
                3, 
                2, 
                1, 
                1, 
                0, 
                0, 
                -1, 
                -1, 
                -1, 
                -1, 
                -1, 
                -1, 
                -1, 
                0, 
                0, 
                0, 
                0, 
                0, 
                0, 
                -1, 
                0, 
                0, 
                0, 
                -1, 
                -1, 
                0, 
                0, 
                0, 
                0, 
                0, 
                0, 
                0, 
                1
            ], 
            "Length": 96, 
            "Z": [
                0, 
                0, 
                0, 
                0, 
                0, 
                0, 
                0, 
                0, 
                0, 
                0, 
                0, 
                0, 
                0, 
                0, 
                0, 
                1, 
                -9, 
                -25, 
                -36, 
                -4, 
                3, 
                14, 
                45, 
                8, 
                -24, 
                -34, 
                -17, 
                12, 
                12, 
                5, 
                2, 
                3, 
                0, 
                -1, 
                -3, 
                0, 
                2, 
                2, 
                1, 
                2, 
                2, 
                2, 
                3, 
                1, 
                -3, 
                -6, 
                -6, 
                -2, 
                2, 
                3, 
                1, 
                -2, 
                -3, 
                -1, 
                0, 
                1, 
                1, 
                -2, 
                -4, 
                -2, 
                0, 
                1, 
                1, 
                0, 
                -1, 
                -1, 
                -1, 
                0, 
                -1, 
                0, 
                0, 
                1, 
                2, 
                2, 
                1, 
                0, 
                0, 
                0, 
                0, 
                0, 
                0, 
                0, 
                0, 
                -1, 
                0, 
                0, 
                0, 
                0, 
                0, 
                0, 
                0, 
                0, 
                0, 
                0, 
                0, 
                0
            ]
        }, 
        "GyroSamples": {
            "Y": [
                -3, 
                -2, 
                5632, 
                5632, 
                5888, 
                5888, 
                6144, 
                5888, 
                5888, 
                6144, 
                6912, 
                6912, 
                7424, 
                6656, 
                0, 
                890, 
                -29644, 
                10233, 
                -14395, 
                -31305, 
                -2600, 
                -11768, 
                -4336, 
                -11000, 
                -6662, 
                7408, 
                12270, 
                -22802, 
                -30999, 
                -21536, 
                -1831, 
                -11041, 
                -25878, 
                16115, 
                -18185, 
                -27655, 
                -31750, 
                -9731, 
                7934, 
                -7937, 
                12027, 
                6901, 
                -12050, 
                29930, 
                -4883, 
                -23566, 
                -25608, 
                17406, 
                -29949, 
                -30970, 
                -14074, 
                4605, 
                3577, 
                -19979, 
                -30989, 
                -28941, 
                -6155, 
                -26375, 
                -116, 
                -6912, 
                -4607, 
                -5631, 
                11778, 
                -29950, 
                -21246, 
                4864, 
                -22529, 
                18430, 
                5630, 
                510, 
                -26625, 
                -25087, 
                750, 
                800, 
                2819, 
                -12286, 
                -25342, 
                -28926, 
                -21502, 
                29186
            ], 
            "X": [
                2047, 
                2047, 
                767, 
                2303, 
                1791, 
                767, 
                767, 
                1535, 
                1279, 
                1023, 
                1535, 
                1791, 
                2047, 
                2559, 
                10239, 
                2047, 
                14847, 
                -14081, 
                23039, 
                -25857, 
                29439, 
                -12289, 
                28415, 
                2559, 
                1279, 
                30207, 
                -1025, 
                -19457, 
                6911, 
                -6145, 
                -1793, 
                -26113, 
                2303, 
                15359, 
                -1, 
                -20737, 
                -22017, 
                -29185, 
                -1, 
                14079, 
                -19457, 
                3839, 
                18943, 
                11007, 
                2047, 
                15615, 
                31487, 
                -14849, 
                -11521, 
                32511, 
                511, 
                -18945, 
                2303, 
                27391, 
                20991, 
                16895, 
                30207, 
                14847, 
                2047, 
                -23809, 
                3071, 
                -29953, 
                15871, 
                -12289, 
                -11265, 
                -16641, 
                25855, 
                -30977, 
                25087, 
                -5633, 
                -5633, 
                8703, 
                2047, 
                2047, 
                4095, 
                -3329, 
                -7169, 
                -12801, 
                -26881, 
                4863
            ], 
            "Length": 80, 
            "Z": [
                27, 
                22, 
                10496, 
                10240, 
                9984, 
                10240, 
                10496, 
                10240, 
                10240, 
                10240, 
                9472, 
                10240, 
                10496, 
                9984, 
                8448, 
                -2005, 
                6028, 
                -31268, 
                -14017, 
                -21642, 
                -11906, 
                -30088, 
                -18563, 
                1576, 
                3565, 
                -9791, 
                -7001, 
                -30813, 
                -8524, 
                -22575, 
                -13064, 
                -26369, 
                -18425, 
                -1774, 
                25885, 
                26407, 
                12077, 
                21800, 
                -5859, 
                30223, 
                -16119, 
                5895, 
                31235, 
                -20225, 
                -531, 
                17149, 
                -7945, 
                -18452, 
                6114, 
                31455, 
                8164, 
                18931, 
                15346, 
                -4880, 
                -17420, 
                9212, 
                -4349, 
                7943, 
                1911, 
                16902, 
                7429, 
                5123, 
                9729, 
                25854, 
                -14596, 
                -24836, 
                -10244, 
                -11779, 
                -28162, 
                12031, 
                -12289, 
                -28929, 
                -184, 
                -207, 
                24063, 
                25598, 
                29438, 
                -28674, 
                -19714, 
                -4097
            ]
        }, 
        "DeviceRevision": 0, 
        "TimeReceivedBySlc": "2018-01-29T21:06:21.267878+00:00", 
        "DeviceType": 0, 
        "Flags": 0, 
        "AccelerometerThreshold": 0, 
        "GyroThreshold": 0, 
        "FirmwareVersion": {
            "Major": 0, 
            "Build": 0, 
            "Minor": 0, 
            "IsModified": false
        }, 
        "TimeCreated_Uncorrected": null
    }, 
    {
        "EventId": 90, 
        "Transform": 5, 
        "TimeCreated": "2018-01-29T21:06:10.702+00:00", 
        "Accelerometer": {
            "TriggerCount": 0, 
            "SampleRateHz": 1000, 
            "Offsets": {
                "Y": 0, 
                "X": 0, 
                "Z": 0
            }
        }, 
        "HardwareId": 210609, 
        "Gyro": {
            "TriggerCount": 0, 
            "SampleRateHz": 765, 
            "Offsets": {
                "Y": 0, 
                "X": 0, 
                "Z": 0
            }
        }, 
        "SerialNumber": "6EPJ", 
        "AccelerometerSamples": {
            "Y": [
                -1, 
                -1, 
                -1, 
                -1, 
                -1, 
                -1, 
                -1, 
                -1, 
                -1, 
                -1, 
                -1, 
                -1, 
                -1, 
                -1, 
                -1, 
                1, 
                64, 
                41, 
                -7, 
                -34, 
                -9, 
                -41, 
                -61, 
                -73, 
                -4, 
                6, 
                26, 
                37, 
                18, 
                -1, 
                5, 
                12, 
                10, 
                4, 
                -4, 
                -10, 
                -12, 
                -15, 
                -18, 
                -19, 
                -15, 
                -9, 
                -3, 
                2, 
                22, 
                27, 
                14, 
                9, 
                7, 
                6, 
                2, 
                -1, 
                -6, 
                -12, 
                -14, 
                -14, 
                -12, 
                -10, 
                -8, 
                -7, 
                -4, 
                -2, 
                -1, 
                0, 
                0, 
                2, 
                2, 
                3, 
                2, 
                3, 
                2, 
                1, 
                0, 
                0, 
                0, 
                -1, 
                -1, 
                -1, 
                -2, 
                -1, 
                -2, 
                -1, 
                -2, 
                -1, 
                -2, 
                -2, 
                -1, 
                -1, 
                -1, 
                -1, 
                -1, 
                0, 
                -1, 
                -1, 
                -1, 
                -1
            ], 
            "X": [
                -1, 
                0, 
                -1, 
                -1, 
                -1, 
                0, 
                0, 
                0, 
                0, 
                -1, 
                -1, 
                0, 
                -1, 
                -1, 
                0, 
                -1, 
                -1, 
                -23, 
                -47, 
                10, 
                -2, 
                6, 
                49, 
                90, 
                16, 
                0, 
                -7, 
                -22, 
                -27, 
                -10, 
                -4, 
                -6, 
                -6, 
                -4, 
                -3, 
                -1, 
                5, 
                11, 
                9, 
                10, 
                7, 
                6, 
                4, 
                1, 
                -1, 
                -7, 
                -7, 
                -6, 
                -8, 
                -7, 
                -7, 
                -7, 
                -8, 
                -9, 
                -9, 
                -6, 
                -2, 
                0, 
                1, 
                2, 
                1, 
                1, 
                1, 
                1, 
                1, 
                1, 
                1, 
                1, 
                1, 
                1, 
                0, 
                -1, 
                -1, 
                -2, 
                -1, 
                -1, 
                -1, 
                -1, 
                -1, 
                -1, 
                -1, 
                -1, 
                -2, 
                -1, 
                -2, 
                -1, 
                -1, 
                -1, 
                -1, 
                -1, 
                -1, 
                -1, 
                0, 
                0, 
                -1, 
                0
            ], 
            "Length": 96, 
            "Z": [
                0, 
                -1, 
                -1, 
                0, 
                0, 
                -1, 
                0, 
                -1, 
                -1, 
                0, 
                0, 
                0, 
                0, 
                0, 
                0, 
                -1, 
                -42, 
                -128, 
                101, 
                127, 
                51, 
                6, 
                -3, 
                22, 
                7, 
                -20, 
                -68, 
                -47, 
                -23, 
                61, 
                106, 
                13, 
                -6, 
                -11, 
                -22, 
                -31, 
                -17, 
                -5, 
                15, 
                27, 
                8, 
                -4, 
                -7, 
                -7, 
                -28, 
                -28, 
                -4, 
                21, 
                28, 
                12, 
                2, 
                -3, 
                -7, 
                -9, 
                -5, 
                1, 
                -2, 
                -1, 
                1, 
                2, 
                3, 
                2, 
                1, 
                0, 
                -1, 
                -1, 
                -1, 
                0, 
                0, 
                1, 
                1, 
                2, 
                1, 
                1, 
                0, 
                1, 
                1, 
                1, 
                1, 
                0, 
                0, 
                0, 
                0, 
                0, 
                0, 
                1, 
                1, 
                0, 
                0, 
                0, 
                0, 
                0, 
                0, 
                0, 
                0, 
                0
            ]
        }, 
        "GyroSamples": {
            "Y": [
                3584, 
                4096, 
                4608, 
                4352, 
                4352, 
                4864, 
                5376, 
                5120, 
                5120, 
                5120, 
                4608, 
                4864, 
                4, 
                4864, 
                4864, 
                4096, 
                5887, 
                14828, 
                -15961, 
                27617, 
                -3236, 
                17522, 
                13390, 
                18431, 
                3317, 
                -6130, 
                3321, 
                18133, 
                30678, 
                -14864, 
                -13308, 
                -13551, 
                -21989, 
                -23538, 
                29961, 
                -246, 
                20493, 
                -14320, 
                21517, 
                -23293, 
                -10141, 
                -21038, 
                28121, 
                -2827, 
                30745, 
                -15822, 
                -25284, 
                -13001, 
                7200, 
                -27132, 
                -3346, 
                -3349, 
                23018, 
                -6421, 
                -7956, 
                -14610, 
                -20750, 
                16117, 
                18422, 
                20471, 
                -10505, 
                507, 
                -30977, 
                4356, 
                23560, 
                -26613, 
                27660, 
                -26355, 
                3110, 
                -8182, 
                16393, 
                -24826, 
                -21757, 
                8448, 
                15358, 
                -1285, 
                -22790, 
                27386, 
                -1464, 
                -12806
            ], 
            "X": [
                1279, 
                1279, 
                1279, 
                2047, 
                1791, 
                1279, 
                1535, 
                2047, 
                2303, 
                2303, 
                2303, 
                2303, 
                2047, 
                2303, 
                2815, 
                2559, 
                13823, 
                11775, 
                -4097, 
                -24833, 
                -23297, 
                32511, 
                2047, 
                -3841, 
                -9729, 
                -11521, 
                17407, 
                20223, 
                -18433, 
                19199, 
                12543, 
                -14081, 
                -22529, 
                9727, 
                21759, 
                18175, 
                -26881, 
                22271, 
                -5377, 
                25087, 
                2047, 
                -21505, 
                -21249, 
                -6657, 
                -1537, 
                23039, 
                -27137, 
                -32257, 
                -27649, 
                -18177, 
                2047, 
                -30209, 
                26879, 
                6143, 
                6911, 
                -25345, 
                30719, 
                30463, 
                -15617, 
                4863, 
                15103, 
                9727, 
                -18945, 
                -21505, 
                -17409, 
                23295, 
                -19457, 
                9727, 
                2047, 
                -9473, 
                4351, 
                -20737, 
                -11265, 
                -4353, 
                30207, 
                14079, 
                26367, 
                5887, 
                2047, 
                -3841
            ], 
            "Length": 80, 
            "Z": [
                17408, 
                17664, 
                17920, 
                17664, 
                17920, 
                17920, 
                17664, 
                17152, 
                17152, 
                17664, 
                17152, 
                16640, 
                18, 
                18176, 
                17920, 
                17920, 
                15104, 
                13568, 
                -11999, 
                2114, 
                1521, 
                -29719, 
                4506, 
                -5105, 
                -19424, 
                -28368, 
                -3779, 
                15408, 
                -4586, 
                -4350, 
                -4624, 
                31207, 
                12531, 
                31258, 
                4626, 
                24070, 
                -22009, 
                24840, 
                -9206, 
                5903, 
                1723, 
                26116, 
                -29660, 
                -30912, 
                -28867, 
                18477, 
                24603, 
                -29955, 
                21497, 
                15859, 
                -4998, 
                7396, 
                -20000, 
                3551, 
                -10521, 
                -22033, 
                -1287, 
                1539, 
                -24310, 
                28686, 
                26127, 
                8977, 
                -30959, 
                -28143, 
                21007, 
                -16884, 
                29193, 
                26886, 
                716, 
                -12031, 
                17153, 
                15104, 
                -11265, 
                17918, 
                6908, 
                13560, 
                25591, 
                -23050, 
                -2730, 
                -28172
            ]
        }, 
        "DeviceRevision": 0, 
        "TimeReceivedBySlc": "2018-01-29T21:07:03.306919+00:00", 
        "DeviceType": 0, 
        "Flags": 0, 
        "AccelerometerThreshold": 0, 
        "GyroThreshold": 0, 
        "FirmwareVersion": {
            "Major": 0, 
            "Build": 0, 
            "Minor": 0, 
            "IsModified": false
        }, 
        "TimeCreated_Uncorrected": null
    }, 
    {
        "EventId": 74, 
        "Transform": 5, 
        "TimeCreated": "2018-01-29T21:06:10.75+00:00", 
        "Accelerometer": {
            "TriggerCount": 0, 
            "SampleRateHz": 1000, 
            "Offsets": {
                "Y": 0, 
                "X": 0, 
                "Z": 0
            }
        }, 
        "HardwareId": 210648, 
        "Gyro": {
            "TriggerCount": 0, 
            "SampleRateHz": 765, 
            "Offsets": {
                "Y": 0, 
                "X": 0, 
                "Z": 0
            }
        }, 
        "SerialNumber": "6EQS", 
        "AccelerometerSamples": {
            "Y": [
                0, 
                1, 
                0, 
                0, 
                1, 
                0, 
                0, 
                0, 
                1, 
                0, 
                0, 
                1, 
                0, 
                0, 
                1, 
                0, 
                -7, 
                -33, 
                14, 
                8, 
                18, 
                30, 
                0, 
                13, 
                4, 
                -19, 
                -5, 
                2, 
                2, 
                3, 
                3, 
                13, 
                6, 
                10, 
                1, 
                -4, 
                -2, 
                2, 
                -1, 
                -3, 
                7, 
                -1, 
                1, 
                4, 
                2, 
                -10, 
                4, 
                -3, 
                0, 
                -3, 
                -2, 
                -4, 
                -3, 
                -4, 
                -3, 
                -2, 
                -2, 
                3, 
                5, 
                -4, 
                0, 
                -3, 
                -2, 
                1, 
                1, 
                1, 
                -2, 
                -2, 
                0, 
                -1, 
                0, 
                0, 
                -1, 
                -1, 
                0, 
                0, 
                1, 
                0, 
                0, 
                1, 
                0, 
                -1, 
                0, 
                -1, 
                -1, 
                0, 
                0, 
                0, 
                0, 
                0, 
                0, 
                0, 
                0, 
                0, 
                0, 
                0
            ], 
            "X": [
                -1, 
                0, 
                0, 
                0, 
                -1, 
                0, 
                -1, 
                0, 
                -1, 
                0, 
                -1, 
                0, 
                -1, 
                -1, 
                0, 
                0, 
                0, 
                71, 
                127, 
                57, 
                -67, 
                -94, 
                -74, 
                -10, 
                -14, 
                -18, 
                -9, 
                -1, 
                21, 
                14, 
                -8, 
                8, 
                3, 
                5, 
                -2, 
                -20, 
                -4, 
                2, 
                1, 
                -9, 
                -3, 
                -4, 
                -4, 
                -4, 
                1, 
                14, 
                26, 
                3, 
                -10, 
                1, 
                -4, 
                -4, 
                -8, 
                -5, 
                -10, 
                -6, 
                -5, 
                3, 
                13, 
                -3, 
                -7, 
                -8, 
                -5, 
                -1, 
                2, 
                -2, 
                -3, 
                -3, 
                2, 
                1, 
                -1, 
                0, 
                1, 
                -1, 
                -1, 
                0, 
                0, 
                0, 
                0, 
                -1, 
                -1, 
                -1, 
                0, 
                0, 
                -1, 
                -1, 
                -1, 
                0, 
                0, 
                0, 
                0, 
                0, 
                0, 
                0, 
                0, 
                0
            ], 
            "Length": 96, 
            "Z": [
                0, 
                0, 
                0, 
                0, 
                0, 
                0, 
                0, 
                0, 
                0, 
                0, 
                0, 
                0, 
                -1, 
                0, 
                0, 
                0, 
                0, 
                98, 
                -32, 
                13, 
                -12, 
                13, 
                -43, 
                -17, 
                -11, 
                -12, 
                28, 
                6, 
                1, 
                8, 
                -19, 
                -9, 
                -27, 
                -12, 
                0, 
                11, 
                6, 
                1, 
                -5, 
                4, 
                -4, 
                8, 
                4, 
                5, 
                -5, 
                -5, 
                17, 
                -8, 
                -7, 
                -2, 
                8, 
                2, 
                -1, 
                2, 
                -2, 
                0, 
                -5, 
                -1, 
                7, 
                2, 
                -6, 
                -2, 
                -2, 
                0, 
                0, 
                -2, 
                -2, 
                -2, 
                -2, 
                -1, 
                0, 
                -1, 
                -2, 
                -1, 
                -1, 
                0, 
                -1, 
                -1, 
                -1, 
                -2, 
                -1, 
                -1, 
                -1, 
                -1, 
                -1, 
                -1, 
                -1, 
                -2, 
                -1, 
                0, 
                -1, 
                0, 
                0, 
                0, 
                0, 
                0
            ]
        }, 
        "GyroSamples": {
            "Y": [
                -1, 
                255, 
                767, 
                255, 
                -257, 
                511, 
                1279, 
                1023, 
                511, 
                511, 
                -257, 
                -2, 
                -257, 
                -769, 
                255, 
                -256, 
                511, 
                -1025, 
                -9, 
                -26368, 
                -17926, 
                27648, 
                -29428, 
                -23797, 
                -14080, 
                -4069, 
                6119, 
                -10014, 
                6121, 
                -21259, 
                -23816, 
                -5384, 
                -5390, 
                1003, 
                -20248, 
                1003, 
                -6930, 
                14321, 
                26866, 
                12275, 
                9718, 
                24825, 
                -18186, 
                13555, 
                -18443, 
                -3797, 
                -20749, 
                7927, 
                -19720, 
                -19206, 
                -12549, 
                22779, 
                -1935, 
                -1542, 
                12795, 
                5627, 
                22779, 
                -28933, 
                30203, 
                -732, 
                -31492, 
                31228, 
                25596, 
                -6915, 
                18429, 
                5373, 
                -14082, 
                -6913, 
                -6401, 
                -10497, 
                -21761, 
                31999, 
                25088, 
                24832, 
                -32000, 
                -28159, 
                -22527, 
                -17919, 
                -18431, 
                -26623
            ], 
            "X": [
                -1025, 
                -1281, 
                -1537, 
                -2305, 
                -2817, 
                -2817, 
                -2817, 
                -2817, 
                -1793, 
                -1793, 
                -1281, 
                2047, 
                -513, 
                -769, 
                -257, 
                255, 
                -769, 
                -1281, 
                2047, 
                11775, 
                14079, 
                20991, 
                -8193, 
                22015, 
                -2561, 
                2047, 
                -2561, 
                -769, 
                25087, 
                9727, 
                30975, 
                26879, 
                -5633, 
                21759, 
                -11777, 
                511, 
                -15361, 
                7679, 
                767, 
                30463, 
                4095, 
                16895, 
                -23041, 
                14079, 
                15103, 
                2047, 
                -11265, 
                11519, 
                30463, 
                -15361, 
                -10241, 
                -8193, 
                2047, 
                21247, 
                14335, 
                29951, 
                15615, 
                22015, 
                -12545, 
                2047, 
                -16129, 
                30463, 
                -513, 
                23295, 
                22527, 
                -24321, 
                -15105, 
                17407, 
                23039, 
                13055, 
                21759, 
                -23297, 
                2047, 
                -15617, 
                -2049, 
                6399, 
                16895, 
                25855, 
                -29953, 
                -19201
            ], 
            "Length": 80, 
            "Z": [
                4863, 
                4608, 
                4864, 
                4352, 
                4095, 
                3840, 
                3584, 
                3072, 
                2816, 
                3072, 
                4095, 
                0, 
                3839, 
                4095, 
                3840, 
                4863, 
                5120, 
                5375, 
                -2, 
                511, 
                10226, 
                -8413, 
                -1232, 
                -24564, 
                -5146, 
                -11416, 
                -2345, 
                -14113, 
                -27185, 
                -795, 
                13036, 
                -12300, 
                32503, 
                -17922, 
                -7164, 
                5890, 
                4350, 
                31231, 
                26622, 
                -9731, 
                30457, 
                -21001, 
                26100, 
                22259, 
                -3847, 
                -1599, 
                28411, 
                -18948, 
                18682, 
                -11525, 
                -3844, 
                31997, 
                -845, 
                -23042, 
                21760, 
                -24319, 
                -10752, 
                -24065, 
                4095, 
                -152, 
                -5889, 
                15359, 
                22015, 
                -23809, 
                -14080, 
                -16896, 
                -24321, 
                32511, 
                22271, 
                17151, 
                12287, 
                16895, 
                26111, 
                31487, 
                31743, 
                30975, 
                28159, 
                24831, 
                23551, 
                22271
            ]
        }, 
        "DeviceRevision": 0, 
        "TimeReceivedBySlc": "2018-01-29T21:06:38.155677+00:00", 
        "DeviceType": 0, 
        "Flags": 0, 
        "AccelerometerThreshold": 0, 
        "GyroThreshold": 0, 
        "FirmwareVersion": {
            "Major": 0, 
            "Build": 0, 
            "Minor": 0, 
            "IsModified": false
        }, 
        "TimeCreated_Uncorrected": null
    }, 
    {
        "EventId": 69, 
        "Transform": 5, 
        "TimeCreated": "2018-01-29T21:06:10.768+00:00", 
        "Accelerometer": {
            "TriggerCount": 0, 
            "SampleRateHz": 1000, 
            "Offsets": {
                "Y": 0, 
                "X": 0, 
                "Z": 0
            }
        }, 
        "HardwareId": 210620, 
        "Gyro": {
            "TriggerCount": 0, 
            "SampleRateHz": 765, 
            "Offsets": {
                "Y": 0, 
                "X": 0, 
                "Z": 0
            }
        }, 
        "SerialNumber": "6EPW", 
        "AccelerometerSamples": {
            "Y": [
                -1, 
                -1, 
                -1, 
                -1, 
                -1, 
                -1, 
                -1, 
                -1, 
                -1, 
                -1, 
                -1, 
                -1, 
                -1, 
                1, 
                0, 
                -3, 
                -8, 
                -17, 
                11, 
                1, 
                -3, 
                -2, 
                0, 
                -3, 
                -3, 
                -5, 
                -4, 
                -4, 
                -3, 
                -2, 
                -2, 
                -1, 
                0, 
                -1, 
                1, 
                1, 
                0, 
                0, 
                0, 
                0, 
                0, 
                0, 
                0, 
                0, 
                0, 
                0, 
                0, 
                -1, 
                -2, 
                1, 
                1, 
                0, 
                -1, 
                0, 
                -1, 
                0, 
                -1, 
                -1, 
                0, 
                0, 
                0, 
                0, 
                0, 
                0, 
                -1, 
                -1, 
                0, 
                0, 
                -1, 
                -1, 
                -1, 
                0, 
                0, 
                0, 
                0, 
                0, 
                0, 
                0, 
                0, 
                0, 
                0, 
                0, 
                0, 
                0, 
                -1, 
                0, 
                -1, 
                0, 
                0, 
                -1, 
                0, 
                -1, 
                -1, 
                -1, 
                -1, 
                -1
            ], 
            "X": [
                -1, 
                -1, 
                -1, 
                -1, 
                -1, 
                -2, 
                -1, 
                -1, 
                -1, 
                -1, 
                -1, 
                -1, 
                -1, 
                1, 
                0, 
                1, 
                10, 
                15, 
                13, 
                -10, 
                -7, 
                -2, 
                -1, 
                -1, 
                -1, 
                0, 
                -2, 
                -5, 
                -5, 
                -3, 
                0, 
                -1, 
                -4, 
                -7, 
                -6, 
                -5, 
                -6, 
                -5, 
                -3, 
                -3, 
                -1, 
                -2, 
                -3, 
                -2, 
                -1, 
                -2, 
                -2, 
                -1, 
                0, 
                -3, 
                -3, 
                -2, 
                -1, 
                -1, 
                0, 
                1, 
                0, 
                0, 
                0, 
                -1, 
                -1, 
                -3, 
                -3, 
                -3, 
                -2, 
                -2, 
                -3, 
                -2, 
                -1, 
                -1, 
                -1, 
                0, 
                -1, 
                -1, 
                -1, 
                -2, 
                -1, 
                -1, 
                -2, 
                -1, 
                -1, 
                -1, 
                -1, 
                -1, 
                -1, 
                -1, 
                -1, 
                -1, 
                -1, 
                0, 
                -1, 
                -1, 
                -1, 
                -1, 
                -1, 
                -1
            ], 
            "Length": 96, 
            "Z": [
                -1, 
                -1, 
                -1, 
                0, 
                -1, 
                -1, 
                0, 
                0, 
                -1, 
                -1, 
                -1, 
                -1, 
                0, 
                1, 
                -15, 
                -6, 
                10, 
                13, 
                -9, 
                -6, 
                2, 
                -6, 
                4, 
                -13, 
                5, 
                4, 
                2, 
                2, 
                0, 
                0, 
                -2, 
                -2, 
                1, 
                3, 
                -3, 
                1, 
                -1, 
                0, 
                2, 
                0, 
                1, 
                0, 
                -2, 
                0, 
                0, 
                -1, 
                0, 
                -1, 
                -1, 
                -1, 
                -3, 
                1, 
                -1, 
                -1, 
                1, 
                -2, 
                -1, 
                0, 
                0, 
                0, 
                -1, 
                -1, 
                -1, 
                0, 
                -1, 
                -1, 
                0, 
                0, 
                -1, 
                -1, 
                -1, 
                0, 
                0, 
                -1, 
                0, 
                -1, 
                -1, 
                0, 
                -1, 
                0, 
                0, 
                -1, 
                0, 
                0, 
                0, 
                0, 
                0, 
                -1, 
                0, 
                -1, 
                0, 
                0, 
                -1, 
                -1, 
                0, 
                -1
            ]
        }, 
        "GyroSamples": {
            "Y": [
                11008, 
                9983, 
                9727, 
                11007, 
                10751, 
                11007, 
                10495, 
                11007, 
                11007, 
                11263, 
                10239, 
                10495, 
                10751, 
                10496, 
                -24831, 
                20996, 
                -27645, 
                32001, 
                13313, 
                28162, 
                -20734, 
                -4094, 
                -23553, 
                -15107, 
                -21509, 
                -6, 
                -1548, 
                12281, 
                23032, 
                -12809, 
                -6410, 
                -30216, 
                25592, 
                19703, 
                13047, 
                23031, 
                -1806, 
                14330, 
                19709, 
                -3, 
                26109, 
                -29442, 
                -12289, 
                -16130, 
                29693, 
                -579, 
                14077, 
                -10754, 
                16126, 
                30463, 
                4095, 
                -4353, 
                5631, 
                12799, 
                7935, 
                -10241, 
                -29442, 
                20222, 
                19198, 
                10238, 
                11006, 
                20222, 
                -26882, 
                -8705, 
                6399, 
                16639, 
                28928, 
                28416, 
                22016, 
                8193, 
                -6143, 
                -12287, 
                -15615, 
                -10238, 
                -4094, 
                617, 
                16386, 
                25090, 
                -30974, 
                -22014
            ], 
            "X": [
                511, 
                -1, 
                -769, 
                -769, 
                -513, 
                -513, 
                -1281, 
                -1025, 
                -1537, 
                -1025, 
                -1281, 
                -1537, 
                -1025, 
                2559, 
                28415, 
                9471, 
                20735, 
                27135, 
                -9217, 
                18943, 
                -25345, 
                -32001, 
                -12801, 
                -4609, 
                -16897, 
                -13313, 
                2047, 
                -17665, 
                -21505, 
                21247, 
                -1281, 
                4095, 
                5119, 
                -30977, 
                -29953, 
                -9473, 
                2047, 
                -32001, 
                4351, 
                16383, 
                -8193, 
                -7169, 
                7935, 
                29439, 
                -3841, 
                2047, 
                -10753, 
                23551, 
                -7169, 
                7423, 
                22271, 
                25087, 
                18687, 
                20735, 
                17407, 
                4351, 
                -8193, 
                -24321, 
                31487, 
                -31489, 
                -28673, 
                -18433, 
                -8961, 
                1023, 
                17663, 
                -28929, 
                8191, 
                30975, 
                -11777, 
                14079, 
                28671, 
                -24577, 
                -10241, 
                18175, 
                26367, 
                2047, 
                22783, 
                16895, 
                14847, 
                18687
            ], 
            "Length": 80, 
            "Z": [
                15616, 
                16128, 
                16384, 
                15872, 
                15360, 
                15360, 
                15872, 
                15360, 
                15104, 
                15360, 
                14848, 
                14848, 
                14848, 
                15616, 
                -768, 
                -27904, 
                22015, 
                -29956, 
                19453, 
                24577, 
                -10492, 
                13315, 
                -19712, 
                -18944, 
                -26109, 
                -22781, 
                960, 
                -11517, 
                24835, 
                -26109, 
                25091, 
                11527, 
                31240, 
                11784, 
                -4857, 
                -3323, 
                742, 
                26880, 
                21246, 
                24061, 
                -27907, 
                29180, 
                -28933, 
                31739, 
                -30213, 
                -1334, 
                -25861, 
                -8965, 
                -15876, 
                23036, 
                -13571, 
                29949, 
                2559, 
                -12545, 
                -27137, 
                25598, 
                20734, 
                27646, 
                -29698, 
                23294, 
                14334, 
                3838, 
                1790, 
                10750, 
                20479, 
                29183, 
                -15361, 
                -10241, 
                -12033, 
                -20481, 
                -27906, 
                -32514, 
                29182, 
                28414, 
                32510, 
                -233, 
                -14081, 
                -3585, 
                3583, 
                7167
            ]
        }, 
        "DeviceRevision": 0, 
        "TimeReceivedBySlc": "2018-01-29T21:06:49.616544+00:00", 
        "DeviceType": 0, 
        "Flags": 0, 
        "AccelerometerThreshold": 0, 
        "GyroThreshold": 0, 
        "FirmwareVersion": {
            "Major": 0, 
            "Build": 0, 
            "Minor": 0, 
            "IsModified": false
        }, 
        "TimeCreated_Uncorrected": null
    }
]