[
    {
        "EventId": 128, 
        "Transform": 5, 
        "TimeCreated": "2018-02-06T17:56:14.996+00:00", 
        "Accelerometer": {
            "TriggerCount": 0, 
            "SampleRateHz": 1000, 
            "Offsets": {
                "Y": 0, 
                "X": 0, 
                "Z": 0
            }
        }, 
        "HardwareId": 210629, 
        "Gyro": {
            "TriggerCount": 0, 
            "SampleRateHz": 765, 
            "Offsets": {
                "Y": 0, 
                "X": 0, 
                "Z": 0
            }
        }, 
        "SerialNumber": "6EQ5", 
        "AccelerometerSamples": {
            "Y": [
                0, 
                0, 
                0, 
                0, 
                1, 
                0, 
                0, 
                0, 
                1, 
                0, 
                0, 
                0, 
                0, 
                0, 
                1, 
                3, 
                11, 
                21, 
                20, 
                15, 
                9, 
                4, 
                0, 
                -2, 
                -3, 
                -2, 
                -4, 
                -6, 
                -6, 
                -8, 
                -7, 
                -6, 
                -3, 
                -2, 
                -1, 
                0, 
                0, 
                1, 
                1, 
                2, 
                2, 
                3, 
                3, 
                1, 
                1, 
                -1, 
                -1, 
                -3, 
                -4, 
                -5, 
                -5, 
                -5, 
                -6, 
                -4, 
                -4, 
                -3, 
                -2, 
                -1, 
                -1, 
                0, 
                0, 
                0, 
                1, 
                0, 
                0, 
                0, 
                0, 
                -1, 
                -1, 
                -1, 
                -1, 
                -1, 
                -2, 
                -2, 
                -1, 
                -2, 
                -2, 
                -2, 
                -1, 
                -1, 
                -1, 
                -1, 
                -1, 
                0, 
                -1, 
                -1, 
                -1, 
                0, 
                -1, 
                0, 
                0, 
                1, 
                0, 
                0, 
                0, 
                0
            ], 
            "X": [
                0, 
                -1, 
                -1, 
                0, 
                0, 
                -1, 
                0, 
                0, 
                0, 
                0, 
                0, 
                0, 
                0, 
                -1, 
                -1, 
                -1, 
                0, 
                0, 
                0, 
                1, 
                -3, 
                -3, 
                -2, 
                -1, 
                0, 
                0, 
                1, 
                2, 
                4, 
                5, 
                5, 
                2, 
                -1, 
                -1, 
                -1, 
                -2, 
                -2, 
                -1, 
                -1, 
                -2, 
                -2, 
                -2, 
                -3, 
                -3, 
                -2, 
                -1, 
                -2, 
                -2, 
                -1, 
                -1, 
                -1, 
                0, 
                1, 
                2, 
                1, 
                1, 
                1, 
                1, 
                1, 
                0, 
                1, 
                1, 
                0, 
                0, 
                0, 
                0, 
                -1, 
                -1, 
                -2, 
                -2, 
                -2, 
                -3, 
                -3, 
                -3, 
                -3, 
                -4, 
                -3, 
                -3, 
                -3, 
                -2, 
                -2, 
                -2, 
                -1, 
                -1, 
                -1, 
                0, 
                0, 
                0, 
                1, 
                1, 
                1, 
                1, 
                1, 
                2, 
                2, 
                1
            ], 
            "Length": 96, 
            "Z": [
                -1, 
                -2, 
                -1, 
                -1, 
                -1, 
                -1, 
                -2, 
                -2, 
                -2, 
                -1, 
                -2, 
                -2, 
                -2, 
                -2, 
                -1, 
                -3, 
                -7, 
                -13, 
                -7, 
                14, 
                10, 
                4, 
                5, 
                3, 
                0, 
                -4, 
                -4, 
                -9, 
                -11, 
                -11, 
                -8, 
                -2, 
                1, 
                2, 
                2, 
                3, 
                2, 
                2, 
                1, 
                0, 
                -2, 
                -4, 
                -4, 
                -4, 
                -2, 
                -1, 
                -2, 
                -2, 
                -2, 
                -3, 
                -3, 
                -4, 
                -4, 
                -4, 
                -2, 
                -1, 
                0, 
                0, 
                0, 
                0, 
                0, 
                0, 
                -1, 
                -1, 
                -2, 
                -2, 
                -3, 
                -3, 
                -3, 
                -3, 
                -4, 
                -3, 
                -3, 
                -1, 
                0, 
                0, 
                0, 
                -1, 
                0, 
                0, 
                0, 
                -1, 
                -1, 
                -1, 
                -1, 
                -2, 
                -2, 
                -2, 
                -3, 
                -3, 
                -3, 
                -3, 
                -2, 
                -2, 
                -2, 
                -1
            ]
        }, 
        "GyroSamples": {
            "Y": [
                20224, 
                23040, 
                23296, 
                -5, 
                7167, 
                -1025, 
                -9473, 
                -17153, 
                -22785, 
                -26881, 
                -26369, 
                -27649, 
                -26625, 
                3071, 
                -10755, 
                31737, 
                -6672, 
                19180, 
                -7908, 
                -10461, 
                -26346, 
                28165, 
                13817, 
                -27145, 
                27134, 
                26886, 
                -2307, 
                13813, 
                22001, 
                -12563, 
                23019, 
                11242, 
                -4331, 
                1268, 
                9466, 
                10753, 
                -1275, 
                17157, 
                -1278, 
                -13316, 
                -26113, 
                -9467, 
                28428, 
                24851, 
                -24044, 
                -28658, 
                -16649, 
                -4092, 
                2541, 
                10990, 
                31730, 
                -24073, 
                18684, 
                -12542, 
                7684, 
                -32252, 
                6404, 
                -4861, 
                -30460, 
                24069, 
                -2555, 
                1084, 
                3840, 
                -15875, 
                30971, 
                -23044, 
                -25858, 
                10497, 
                5122, 
                29954, 
                2306, 
                -25854, 
                7682, 
                -26109, 
                -6909, 
                -8445, 
                603, 
                -25343, 
                23809, 
                14850
            ], 
            "X": [
                2559, 
                1791, 
                511, 
                2047, 
                -4353, 
                -5889, 
                -6401, 
                -5377, 
                -4865, 
                -6657, 
                -6401, 
                -5633, 
                -4353, 
                -30977, 
                -26113, 
                2047, 
                14591, 
                20479, 
                -5121, 
                16127, 
                15103, 
                255, 
                9215, 
                17663, 
                -15617, 
                -23809, 
                8959, 
                -19713, 
                29695, 
                -769, 
                10239, 
                2303, 
                2047, 
                19455, 
                32255, 
                18943, 
                -1025, 
                -8193, 
                767, 
                -1537, 
                22783, 
                10495, 
                -2561, 
                -27393, 
                -9473, 
                6655, 
                16127, 
                2047, 
                17919, 
                18431, 
                4607, 
                15103, 
                19455, 
                -13057, 
                1791, 
                20735, 
                8191, 
                -2817, 
                18943, 
                6143, 
                -4609, 
                2047, 
                -2817, 
                -25345, 
                -9729, 
                21247, 
                10751, 
                -29185, 
                24063, 
                -23297, 
                -23809, 
                -24321, 
                -10753, 
                19455, 
                -22017, 
                12287, 
                2047, 
                -22273, 
                -27137, 
                19711
            ], 
            "Length": 80, 
            "Z": [
                2048, 
                1792, 
                2560, 
                77, 
                8960, 
                11519, 
                13567, 
                14591, 
                15359, 
                15871, 
                14847, 
                14079, 
                15359, 
                21760, 
                -10752, 
                8963, 
                22021, 
                -19971, 
                -3624, 
                -25896, 
                -10014, 
                26094, 
                -16394, 
                -14339, 
                -19961, 
                -17398, 
                -12031, 
                -32260, 
                -13315, 
                15620, 
                -10225, 
                4377, 
                8891, 
                11810, 
                -28131, 
                -493, 
                6918, 
                -4355, 
                7159, 
                5364, 
                29939, 
                17393, 
                -17, 
                17132, 
                18664, 
                2532, 
                12003, 
                -6307, 
                13548, 
                -7183, 
                -13322, 
                -6149, 
                10240, 
                -28153, 
                -26357, 
                20494, 
                -23278, 
                -26347, 
                18969, 
                -15332, 
                -27876, 
                6595, 
                5908, 
                23820, 
                -8699, 
                -19713, 
                -10757, 
                -29961, 
                -2826, 
                29429, 
                7925, 
                1524, 
                13044, 
                -19213, 
                6642, 
                14322, 
                -3303, 
                3827, 
                24564, 
                -24843
            ]
        }, 
        "DeviceRevision": 0, 
        "TimeReceivedBySlc": "2018-02-06T17:57:09.165228+00:00", 
        "DeviceType": 0, 
        "Flags": 0, 
        "AccelerometerThreshold": 0, 
        "GyroThreshold": 0, 
        "FirmwareVersion": {
            "Major": 0, 
            "Build": 0, 
            "Minor": 0, 
            "IsModified": false
        }, 
        "TimeCreated_Uncorrected": null
    }, 
    {
        "EventId": 132, 
        "Transform": 5, 
        "TimeCreated": "2018-02-06T17:56:15.02+00:00", 
        "Accelerometer": {
            "TriggerCount": 0, 
            "SampleRateHz": 1000, 
            "Offsets": {
                "Y": 0, 
                "X": 0, 
                "Z": 0
            }
        }, 
        "HardwareId": 210648, 
        "Gyro": {
            "TriggerCount": 0, 
            "SampleRateHz": 765, 
            "Offsets": {
                "Y": 0, 
                "X": 0, 
                "Z": 0
            }
        }, 
        "SerialNumber": "6EQS", 
        "AccelerometerSamples": {
            "Y": [
                0, 
                0, 
                0, 
                0, 
                0, 
                0, 
                0, 
                0, 
                0, 
                0, 
                0, 
                1, 
                1, 
                0, 
                1, 
                2, 
                3, 
                5, 
                5, 
                5, 
                7, 
                4, 
                -18, 
                -5, 
                0, 
                -3, 
                -1, 
                4, 
                8, 
                0, 
                -5, 
                -1, 
                -2, 
                0, 
                1, 
                1, 
                0, 
                0, 
                -2, 
                -2, 
                -2, 
                -1, 
                0, 
                1, 
                1, 
                1, 
                1, 
                1, 
                2, 
                3, 
                2, 
                2, 
                2, 
                1, 
                1, 
                1, 
                0, 
                2, 
                0, 
                0, 
                -1, 
                0, 
                0, 
                0, 
                0, 
                -1, 
                0, 
                -1, 
                -1, 
                -1, 
                -1, 
                -1, 
                -1, 
                -1, 
                0, 
                0, 
                0, 
                0, 
                1, 
                0, 
                0, 
                0, 
                0, 
                0, 
                1, 
                0, 
                1, 
                0, 
                0, 
                0, 
                1, 
                1, 
                1, 
                2, 
                1, 
                0
            ], 
            "X": [
                0, 
                0, 
                -1, 
                0, 
                0, 
                0, 
                0, 
                0, 
                -1, 
                0, 
                1, 
                0, 
                0, 
                0, 
                0, 
                0, 
                -2, 
                -2, 
                -5, 
                -6, 
                -14, 
                -13, 
                -58, 
                -4, 
                -4, 
                1, 
                13, 
                16, 
                24, 
                22, 
                11, 
                5, 
                7, 
                0, 
                0, 
                1, 
                0, 
                -3, 
                -4, 
                -3, 
                0, 
                0, 
                1, 
                2, 
                3, 
                3, 
                3, 
                3, 
                3, 
                3, 
                5, 
                2, 
                2, 
                2, 
                1, 
                2, 
                1, 
                0, 
                0, 
                -2, 
                -2, 
                -2, 
                -2, 
                -1, 
                -1, 
                -1, 
                -1, 
                -1, 
                -1, 
                -1, 
                -1, 
                -1, 
                -1, 
                -1, 
                -1, 
                0, 
                0, 
                -1, 
                0, 
                0, 
                0, 
                0, 
                0, 
                0, 
                0, 
                0, 
                0, 
                0, 
                1, 
                1, 
                0, 
                0, 
                1, 
                0, 
                -1, 
                -1
            ], 
            "Length": 96, 
            "Z": [
                0, 
                0, 
                0, 
                0, 
                0, 
                0, 
                0, 
                -2, 
                0, 
                0, 
                0, 
                0, 
                0, 
                0, 
                0, 
                -1, 
                -13, 
                -14, 
                -22, 
                -23, 
                -21, 
                -7, 
                104, 
                28, 
                2, 
                14, 
                -16, 
                -37, 
                -17, 
                6, 
                7, 
                5, 
                1, 
                1, 
                -2, 
                -6, 
                -9, 
                0, 
                6, 
                7, 
                4, 
                4, 
                3, 
                -1, 
                -2, 
                -2, 
                -2, 
                -1, 
                -3, 
                -2, 
                -3, 
                0, 
                0, 
                -2, 
                -1, 
                -1, 
                -4, 
                1, 
                2, 
                2, 
                1, 
                1, 
                0, 
                0, 
                -2, 
                1, 
                0, 
                1, 
                1, 
                1, 
                1, 
                0, 
                -1, 
                0, 
                -1, 
                0, 
                1, 
                0, 
                0, 
                0, 
                0, 
                0, 
                0, 
                0, 
                -1, 
                0, 
                0, 
                0, 
                1, 
                -1, 
                2, 
                2, 
                -1, 
                -3, 
                -2, 
                0
            ]
        }, 
        "GyroSamples": {
            "Y": [
                511, 
                1535, 
                1279, 
                1791, 
                2303, 
                3071, 
                2815, 
                3071, 
                -20, 
                5631, 
                6143, 
                4863, 
                8960, 
                8703, 
                6911, 
                12, 
                768, 
                -2048, 
                1279, 
                -5890, 
                -29703, 
                18932, 
                -8460, 
                8158, 
                23035, 
                -23788, 
                -19688, 
                20754, 
                2822, 
                3040, 
                -19445, 
                27658, 
                -19447, 
                29190, 
                5892, 
                20738, 
                -27392, 
                -3070, 
                1540, 
                -1275, 
                6918, 
                12550, 
                26630, 
                -18426, 
                -26363, 
                -6396, 
                6659, 
                26114, 
                -22527, 
                12032, 
                -19971, 
                32764, 
                -9476, 
                22269, 
                22525, 
                22013, 
                -30979, 
                -4867, 
                32253, 
                30206, 
                4095, 
                4608, 
                9216, 
                -4095, 
                -2303, 
                27649, 
                -9727, 
                2818, 
                -3070, 
                12546, 
                31746, 
                12033, 
                30465, 
                -15104, 
                -4608, 
                -20736, 
                -22016, 
                21760, 
                -23808, 
                27391
            ], 
            "X": [
                -1281, 
                -4353, 
                -5889, 
                -7681, 
                -8961, 
                -8961, 
                -9217, 
                -8449, 
                2047, 
                -1537, 
                -1281, 
                -257, 
                1535, 
                -513, 
                -257, 
                2047, 
                2559, 
                255, 
                -10497, 
                28415, 
                -5377, 
                7935, 
                2047, 
                -17921, 
                -20481, 
                -23041, 
                19199, 
                -18433, 
                21759, 
                2047, 
                -6913, 
                26623, 
                1023, 
                -16897, 
                -3585, 
                28415, 
                -6401, 
                -5633, 
                28415, 
                -17921, 
                -26881, 
                -21249, 
                29695, 
                14079, 
                29439, 
                -17921, 
                -21761, 
                -22017, 
                -14849, 
                28671, 
                11263, 
                13311, 
                -20737, 
                26367, 
                -20737, 
                -24577, 
                12031, 
                18175, 
                -14593, 
                -18433, 
                -11521, 
                -26881, 
                -3329, 
                8959, 
                25855, 
                -30209, 
                -15873, 
                7679, 
                -31745, 
                28927, 
                2559, 
                24063, 
                4095, 
                -16897, 
                31743, 
                26879, 
                14079, 
                6655, 
                15871, 
                13567
            ], 
            "Length": 80, 
            "Z": [
                -2560, 
                -3328, 
                -2816, 
                -2560, 
                -1536, 
                -768, 
                256, 
                0, 
                17, 
                1536, 
                3072, 
                6144, 
                9216, 
                10752, 
                12800, 
                14, 
                19968, 
                19711, 
                18944, 
                -24576, 
                -18173, 
                25617, 
                18818, 
                -3278, 
                20191, 
                1482, 
                14309, 
                30723, 
                -27385, 
                -3361, 
                -32270, 
                -7946, 
                8954, 
                -2565, 
                -2563, 
                20223, 
                -21251, 
                28411, 
                20988, 
                -21764, 
                -3843, 
                15356, 
                -5893, 
                27897, 
                -15368, 
                2295, 
                -12041, 
                -19978, 
                15350, 
                4855, 
                17400, 
                15351, 
                18422, 
                18935, 
                3064, 
                19705, 
                27898, 
                -29956, 
                3324, 
                -16900, 
                26877, 
                -1026, 
                -32513, 
                -3585, 
                -26112, 
                -2815, 
                27649, 
                -3582, 
                -31487, 
                21762, 
                20994, 
                -8189, 
                -30205, 
                11011, 
                -11261, 
                -29693, 
                -29437, 
                -30717, 
                -31997, 
                16388
            ]
        }, 
        "DeviceRevision": 0, 
        "TimeReceivedBySlc": "2018-02-06T17:56:56.897343+00:00", 
        "DeviceType": 0, 
        "Flags": 0, 
        "AccelerometerThreshold": 0, 
        "GyroThreshold": 0, 
        "FirmwareVersion": {
            "Major": 0, 
            "Build": 0, 
            "Minor": 0, 
            "IsModified": false
        }, 
        "TimeCreated_Uncorrected": null
    }, 
    {
        "EventId": 147, 
        "Transform": 5, 
        "TimeCreated": "2018-02-06T17:56:15.085+00:00", 
        "Accelerometer": {
            "TriggerCount": 0, 
            "SampleRateHz": 1000, 
            "Offsets": {
                "Y": 0, 
                "X": 0, 
                "Z": 0
            }
        }, 
        "HardwareId": 210609, 
        "Gyro": {
            "TriggerCount": 0, 
            "SampleRateHz": 765, 
            "Offsets": {
                "Y": 0, 
                "X": 0, 
                "Z": 0
            }
        }, 
        "SerialNumber": "6EPJ", 
        "AccelerometerSamples": {
            "Y": [
                -1, 
                -1, 
                -1, 
                -2, 
                -2, 
                -1, 
                -2, 
                -1, 
                -1, 
                -1, 
                -1, 
                -2, 
                -1, 
                -1, 
                -1, 
                0, 
                2, 
                5, 
                8, 
                1, 
                -3, 
                -3, 
                -6, 
                -11, 
                -6, 
                -1, 
                1, 
                2, 
                3, 
                3, 
                2, 
                0, 
                -2, 
                -12, 
                1, 
                1, 
                -1, 
                -1, 
                0, 
                -1, 
                -3, 
                -4, 
                -4, 
                -3, 
                -2, 
                -1, 
                0, 
                -1, 
                0, 
                0, 
                -5, 
                -3, 
                1, 
                1, 
                -3, 
                -2, 
                -1, 
                -2, 
                -3, 
                -2, 
                -2, 
                -2, 
                -2, 
                -2, 
                -3, 
                -3, 
                -4, 
                -4, 
                -3, 
                -3, 
                -3, 
                -3, 
                -3, 
                -3, 
                -2, 
                -2, 
                -2, 
                -2, 
                -2, 
                -1, 
                -1, 
                -2, 
                -2, 
                -1, 
                -1, 
                -2, 
                -3, 
                -1, 
                -2, 
                -1, 
                0, 
                -1, 
                -1, 
                -2, 
                -1, 
                -1
            ], 
            "X": [
                -1, 
                -1, 
                -1, 
                -1, 
                -1, 
                -1, 
                -1, 
                -1, 
                -1, 
                -1, 
                0, 
                -1, 
                -1, 
                -1, 
                -1, 
                -2, 
                -4, 
                -6, 
                -6, 
                -4, 
                -3, 
                -4, 
                -5, 
                -3, 
                -1, 
                -3, 
                -1, 
                0, 
                1, 
                1, 
                0, 
                -1, 
                -1, 
                2, 
                2, 
                -6, 
                -4, 
                -2, 
                -3, 
                -5, 
                -7, 
                -4, 
                -3, 
                -4, 
                -3, 
                -2, 
                -1, 
                0, 
                0, 
                0, 
                1, 
                5, 
                2, 
                1, 
                3, 
                4, 
                3, 
                2, 
                2, 
                3, 
                2, 
                2, 
                2, 
                1, 
                1, 
                1, 
                2, 
                1, 
                1, 
                1, 
                1, 
                1, 
                1, 
                1, 
                1, 
                1, 
                1, 
                1, 
                1, 
                1, 
                1, 
                0, 
                0, 
                0, 
                0, 
                0, 
                1, 
                0, 
                -1, 
                -1, 
                -1, 
                -1, 
                -1, 
                -1, 
                -1, 
                -1
            ], 
            "Length": 96, 
            "Z": [
                -1, 
                0, 
                -1, 
                1, 
                0, 
                0, 
                0, 
                0, 
                0, 
                0, 
                -1, 
                -1, 
                0, 
                0, 
                0, 
                -4, 
                -10, 
                -14, 
                -14, 
                -2, 
                8, 
                2, 
                -3, 
                -7, 
                -7, 
                -3, 
                0, 
                2, 
                6, 
                6, 
                5, 
                4, 
                3, 
                -1, 
                -3, 
                -5, 
                0, 
                2, 
                -3, 
                -6, 
                -5, 
                -1, 
                1, 
                3, 
                4, 
                4, 
                3, 
                3, 
                3, 
                2, 
                2, 
                -1, 
                -1, 
                0, 
                1, 
                1, 
                1, 
                1, 
                1, 
                1, 
                1, 
                1, 
                1, 
                2, 
                2, 
                2, 
                1, 
                0, 
                1, 
                1, 
                2, 
                1, 
                1, 
                1, 
                1, 
                1, 
                1, 
                1, 
                1, 
                1, 
                0, 
                1, 
                1, 
                0, 
                0, 
                0, 
                0, 
                0, 
                0, 
                -1, 
                0, 
                0, 
                0, 
                0, 
                0, 
                1
            ]
        }, 
        "GyroSamples": {
            "Y": [
                2304, 
                3072, 
                3840, 
                2560, 
                2048, 
                2816, 
                2048, 
                768, 
                2303, 
                -11, 
                7167, 
                6911, 
                7423, 
                8703, 
                7679, 
                18431, 
                20991, 
                -1284, 
                -20991, 
                -17665, 
                -19205, 
                19964, 
                -21498, 
                -17399, 
                18675, 
                -30740, 
                21745, 
                -267, 
                520, 
                -9210, 
                16129, 
                16635, 
                -18958, 
                -24845, 
                -2046, 
                21770, 
                23811, 
                -1007, 
                3066, 
                3322, 
                4347, 
                3580, 
                -3844, 
                29435, 
                -1541, 
                -17669, 
                -1663, 
                -28166, 
                -26373, 
                4603, 
                -25349, 
                -22021, 
                15611, 
                -8964, 
                -1795, 
                -5378, 
                11519, 
                -1793, 
                29184, 
                -18176, 
                -1023, 
                14338, 
                -25342, 
                8194, 
                -25342, 
                758, 
                9987, 
                -15613, 
                29187, 
                20227, 
                -23549, 
                17155, 
                17668, 
                29445, 
                1497, 
                -20987, 
                -5883, 
                -22779, 
                -16379, 
                -29691
            ], 
            "X": [
                4351, 
                3327, 
                3071, 
                3327, 
                2815, 
                2047, 
                1791, 
                1023, 
                -1281, 
                2047, 
                -6145, 
                -7937, 
                -10241, 
                -11009, 
                -12033, 
                -15361, 
                21759, 
                -29441, 
                767, 
                -257, 
                -29697, 
                -6401, 
                11007, 
                -30721, 
                25855, 
                -16897, 
                -28161, 
                2047, 
                -32513, 
                -14081, 
                31743, 
                23807, 
                16895, 
                -27649, 
                28671, 
                -19457, 
                -29697, 
                2047, 
                9727, 
                -18689, 
                -12033, 
                -11521, 
                -15617, 
                -23041, 
                6655, 
                -25601, 
                2047, 
                4351, 
                6911, 
                11775, 
                13823, 
                25855, 
                -5889, 
                -30721, 
                15359, 
                8703, 
                767, 
                -23809, 
                1279, 
                -3073, 
                -28161, 
                511, 
                18687, 
                31743, 
                -19969, 
                2047, 
                23295, 
                -32257, 
                -19457, 
                -12545, 
                -11521, 
                -2049, 
                24319, 
                -24833, 
                2047, 
                -9985, 
                -29441, 
                12543, 
                7167, 
                10495
            ], 
            "Length": 80, 
            "Z": [
                21248, 
                22016, 
                21760, 
                20224, 
                18688, 
                18176, 
                16640, 
                15360, 
                14848, 
                17, 
                11264, 
                10496, 
                11008, 
                13824, 
                16640, 
                18432, 
                26626, 
                -19697, 
                -19704, 
                24828, 
                -12042, 
                -22030, 
                -32536, 
                -16413, 
                -530, 
                17392, 
                -16402, 
                -4777, 
                -1550, 
                19707, 
                24837, 
                -11754, 
                21035, 
                -27084, 
                -6359, 
                -22500, 
                -31980, 
                2729, 
                10489, 
                23799, 
                -16392, 
                22010, 
                13051, 
                -27139, 
                23805, 
                -17663, 
                2080, 
                -27894, 
                23050, 
                10, 
                25609, 
                18441, 
                -17143, 
                -19193, 
                -25339, 
                24067, 
                -8958, 
                18688, 
                -19200, 
                5375, 
                21246, 
                -14082, 
                18429, 
                -5635, 
                -22788, 
                -1012, 
                28411, 
                30714, 
                32506, 
                29946, 
                16378, 
                15355, 
                -21508, 
                22781, 
                -470, 
                26110, 
                9470, 
                -14850, 
                -27139, 
                -17924
            ]
        }, 
        "DeviceRevision": 0, 
        "TimeReceivedBySlc": "2018-02-06T17:56:29.729463+00:00", 
        "DeviceType": 0, 
        "Flags": 0, 
        "AccelerometerThreshold": 0, 
        "GyroThreshold": 0, 
        "FirmwareVersion": {
            "Major": 0, 
            "Build": 0, 
            "Minor": 0, 
            "IsModified": false
        }, 
        "TimeCreated_Uncorrected": null
    }, 
    {
        "EventId": 136, 
        "Transform": 5, 
        "TimeCreated": "2018-02-06T17:56:15.125+00:00", 
        "Accelerometer": {
            "TriggerCount": 0, 
            "SampleRateHz": 1000, 
            "Offsets": {
                "Y": 0, 
                "X": 0, 
                "Z": 0
            }
        }, 
        "HardwareId": 210620, 
        "Gyro": {
            "TriggerCount": 0, 
            "SampleRateHz": 765, 
            "Offsets": {
                "Y": 0, 
                "X": 0, 
                "Z": 0
            }
        }, 
        "SerialNumber": "6EPW", 
        "AccelerometerSamples": {
            "Y": [
                -1, 
                -1, 
                -1, 
                -1, 
                -1, 
                -1, 
                -1, 
                -1, 
                -1, 
                -1, 
                -1, 
                -1, 
                -1, 
                -1, 
                -1, 
                -2, 
                -2, 
                -1, 
                -2, 
                -1, 
                -1, 
                0, 
                0, 
                -1, 
                -2, 
                -1, 
                -3, 
                -2, 
                -2, 
                -2, 
                -1, 
                -1, 
                -1, 
                -1, 
                -1, 
                0, 
                1, 
                0, 
                -2, 
                -2, 
                -2, 
                1, 
                -1, 
                -1, 
                -1, 
                0, 
                -1, 
                0, 
                -1, 
                -1, 
                0, 
                -1, 
                0, 
                0, 
                0, 
                0, 
                0, 
                -1, 
                0, 
                0, 
                1, 
                1, 
                0, 
                0, 
                0, 
                0, 
                0, 
                -1, 
                -1, 
                0, 
                -1, 
                -1, 
                0, 
                0, 
                0, 
                -1, 
                -1, 
                0, 
                -1, 
                -1, 
                -1, 
                -1, 
                -1, 
                -1, 
                -1, 
                -1, 
                -1, 
                -1, 
                -1, 
                -1, 
                -1, 
                -1, 
                -1, 
                -1, 
                -1, 
                -1
            ], 
            "X": [
                -1, 
                -1, 
                -1, 
                -2, 
                -1, 
                -1, 
                -1, 
                -1, 
                -1, 
                -1, 
                -2, 
                -1, 
                -1, 
                -2, 
                -2, 
                -5, 
                -9, 
                -8, 
                -9, 
                -7, 
                -1, 
                -3, 
                -4, 
                -5, 
                -4, 
                -6, 
                -6, 
                -6, 
                -4, 
                -1, 
                2, 
                2, 
                1, 
                0, 
                0, 
                -1, 
                1, 
                3, 
                4, 
                3, 
                2, 
                1, 
                0, 
                -1, 
                0, 
                -1, 
                -1, 
                0, 
                0, 
                1, 
                1, 
                0, 
                0, 
                0, 
                1, 
                1, 
                1, 
                1, 
                2, 
                1, 
                1, 
                1, 
                0, 
                0, 
                0, 
                0, 
                1, 
                1, 
                1, 
                0, 
                1, 
                0, 
                0, 
                0, 
                0, 
                0, 
                1, 
                0, 
                0, 
                0, 
                0, 
                0, 
                0, 
                0, 
                -1, 
                -1, 
                0, 
                -1, 
                0, 
                -1, 
                -1, 
                -1, 
                -1, 
                -2, 
                -2, 
                -2
            ], 
            "Length": 96, 
            "Z": [
                -1, 
                -1, 
                -1, 
                0, 
                0, 
                0, 
                -1, 
                0, 
                -1, 
                -1, 
                -1, 
                -1, 
                0, 
                -1, 
                -1, 
                -1, 
                0, 
                -2, 
                -1, 
                0, 
                1, 
                -1, 
                -1, 
                1, 
                0, 
                0, 
                -2, 
                -1, 
                0, 
                0, 
                -2, 
                -2, 
                -1, 
                -2, 
                -1, 
                -1, 
                -2, 
                -1, 
                1, 
                -1, 
                -1, 
                0, 
                -1, 
                -2, 
                -1, 
                -1, 
                -1, 
                -2, 
                0, 
                0, 
                -1, 
                -1, 
                0, 
                -1, 
                -1, 
                0, 
                -1, 
                0, 
                -1, 
                0, 
                -1, 
                0, 
                0, 
                0, 
                -1, 
                0, 
                -1, 
                -1, 
                0, 
                -1, 
                -1, 
                0, 
                -1, 
                -1, 
                -1, 
                -1, 
                0, 
                -1, 
                -1, 
                -1, 
                -1, 
                -1, 
                0, 
                -1, 
                -1, 
                -1, 
                -1, 
                -1, 
                0, 
                -1, 
                -1, 
                -1, 
                0, 
                -1, 
                0, 
                0
            ]
        }, 
        "GyroSamples": {
            "Y": [
                16639, 
                15359, 
                13823, 
                11263, 
                8703, 
                5375, 
                2559, 
                255, 
                -1281, 
                -2817, 
                -4097, 
                -3585, 
                -2305, 
                -1537, 
                255, 
                -14081, 
                -332, 
                8702, 
                15871, 
                -13568, 
                -5120, 
                13823, 
                24831, 
                -25090, 
                6400, 
                98, 
                -8704, 
                9984, 
                29439, 
                -8194, 
                2302, 
                -20226, 
                9214, 
                -18434, 
                20734, 
                -236, 
                -21505, 
                22270, 
                22014, 
                -20738, 
                -11522, 
                -10498, 
                -15618, 
                -17922, 
                -9986, 
                16638, 
                -30210, 
                -9730, 
                10750, 
                32766, 
                -8450, 
                18430, 
                7934, 
                28926, 
                -18178, 
                -234, 
                15615, 
                -29697, 
                -9728, 
                25088, 
                -24832, 
                -9215, 
                7169, 
                23297, 
                -26367, 
                546, 
                19714, 
                -30462, 
                -15102, 
                514, 
                16642, 
                27906, 
                -28158, 
                -255, 
                425, 
                25089, 
                -31231, 
                -23295, 
                -16383, 
                -13055
            ], 
            "X": [
                -2049, 
                -2305, 
                -1537, 
                -3585, 
                -4097, 
                -4865, 
                -4609, 
                -6401, 
                -7169, 
                -7681, 
                -9217, 
                -8705, 
                -8193, 
                -9985, 
                -11009, 
                -30977, 
                2047, 
                28927, 
                -19713, 
                27647, 
                -21249, 
                -6145, 
                11775, 
                -8449, 
                16383, 
                2047, 
                30975, 
                8191, 
                8959, 
                -23553, 
                -15873, 
                15103, 
                10495, 
                -30209, 
                -4097, 
                2047, 
                1279, 
                -3841, 
                -10753, 
                -22785, 
                -19457, 
                -24577, 
                -24833, 
                32767, 
                13311, 
                10751, 
                18943, 
                24831, 
                23551, 
                25855, 
                28927, 
                25343, 
                26367, 
                -26881, 
                -12033, 
                2047, 
                28671, 
                -15617, 
                2815, 
                -26881, 
                -6657, 
                12031, 
                28927, 
                -20737, 
                -5633, 
                2047, 
                27135, 
                31743, 
                -32513, 
                31743, 
                26111, 
                14847, 
                2047, 
                -18177, 
                2047, 
                -28673, 
                28671, 
                21759, 
                18943, 
                18175
            ], 
            "Length": 80, 
            "Z": [
                19200, 
                19200, 
                18432, 
                17408, 
                17408, 
                15616, 
                14336, 
                13824, 
                12287, 
                10751, 
                9727, 
                8959, 
                8703, 
                8703, 
                5376, 
                -14849, 
                -111, 
                6398, 
                12029, 
                17404, 
                19451, 
                -9733, 
                -11014, 
                -18951, 
                -17416, 
                -2309, 
                -6155, 
                19445, 
                17653, 
                -3083, 
                -11786, 
                -7178, 
                -23305, 
                13815, 
                -30728, 
                -1807, 
                12025, 
                -3590, 
                15867, 
                -32261, 
                -16645, 
                -6917, 
                -1285, 
                2043, 
                3835, 
                28924, 
                -13316, 
                14588, 
                -27139, 
                -4867, 
                20221, 
                -14594, 
                5631, 
                -7937, 
                -17665, 
                -7, 
                24320, 
                5120, 
                -22528, 
                -22783, 
                12289, 
                -13311, 
                26626, 
                -254, 
                -28926, 
                727, 
                -8189, 
                13315, 
                -32253, 
                -13308, 
                3332, 
                12804, 
                17668, 
                27396, 
                1339, 
                15109, 
                -1787, 
                -15099, 
                -19707, 
                -18427
            ]
        }, 
        "DeviceRevision": 0, 
        "TimeReceivedBySlc": "2018-02-06T17:56:43.174482+00:00", 
        "DeviceType": 0, 
        "Flags": 0, 
        "AccelerometerThreshold": 0, 
        "GyroThreshold": 0, 
        "FirmwareVersion": {
            "Major": 0, 
            "Build": 0, 
            "Minor": 0, 
            "IsModified": false
        }, 
        "TimeCreated_Uncorrected": null
    }
]